MANIFEST.in
README.txt
setup.cfg
setup.py
comm_libs/__init__.py
comm_libs/codec_utils.py
comm_libs/comm_utils.py
comm_libs/contract.py
comm_libs/db_utils.py
comm_libs/django_wrap.py
comm_libs/exception.py
comm_libs/file_utils.py
comm_libs/log_tool.py
comm_libs/price_utils.py
comm_libs/regular_utils.py
comm_libs/rsa_utils.py
comm_libs/security.py
comm_libs/sendmail.py
comm_libs/session.py
comm_libs/string_utils.py
comm_libs/subrent_pay_date_amend.py
comm_libs/template_msg.py
comm_libs/time_utils.py
comm_libs.egg-info/PKG-INFO
comm_libs.egg-info/SOURCES.txt
comm_libs.egg-info/dependency_links.txt
comm_libs.egg-info/top_level.txt