Metadata-Version: 1.0
Name: comm-libs
Version: 1.1.3
Summary: comm_libs
Home-page: UNKNOWN
Author: 1024
Author-email: UNKNOWN
License: LICENSE.txt
Platform: UNKNOWN
